<?xml version="1.0" encoding="UTF-8"?>
<objects serializationModel="Studio.02.03.00">
	<object class="AudioFile" id="{7d9a35fc-c86e-4bce-9197-c4a34da5ee81}">
		<property name="assetPath">
			<value>Jugador/Alarma.wav</value>
		</property>
		<property name="frequencyInKHz">
			<value>48</value>
		</property>
		<property name="channelCount">
			<value>2</value>
		</property>
		<property name="length">
			<value>2</value>
		</property>
		<relationship name="masterAssetFolder">
			<destination>{92f023e3-9311-4359-9174-003d1cfe14c3}</destination>
		</relationship>
	</object>
</objects>
